hbrowser/__init__.py
hbrowser/beep.py
hbrowser/exceptions.py
hbrowser/py.typed
hbrowser/gallery/__init__.py
hbrowser/gallery/driver_base.py
hbrowser/gallery/eh_driver.py
hbrowser/gallery/exh_driver.py
hbrowser/gallery/models.py
hbrowser/gallery/py.typed
hbrowser/gallery/browser/__init__.py
hbrowser/gallery/browser/ban_handler.py
hbrowser/gallery/browser/chrome_manager.py
hbrowser/gallery/browser/factory.py
hbrowser/gallery/browser/py.typed
hbrowser/gallery/captcha/__init__.py
hbrowser/gallery/captcha/constants.py
hbrowser/gallery/captcha/detector.py
hbrowser/gallery/captcha/manager.py
hbrowser/gallery/captcha/models.py
hbrowser/gallery/captcha/py.typed
hbrowser/gallery/captcha/solver_interface.py
hbrowser/gallery/captcha/adapters/__init__.py
hbrowser/gallery/captcha/adapters/twocaptcha_adapter.py
hbrowser/gallery/utils/__init__.py
hbrowser/gallery/utils/log.py
hbrowser/gallery/utils/py.typed
hbrowser/gallery/utils/url.py
hbrowser/gallery/utils/window.py
hbrowser-0.11.7.dist-info/licenses/LICENSE
hvbrowser/__init__.py
hvbrowser/hv.py
hvbrowser/hv_battle.py
hvbrowser/hv_battle_action_manager.py
hvbrowser/hv_battle_buff_manager.py
hvbrowser/hv_battle_item_provider.py
hvbrowser/hv_battle_observer_pattern.py
hvbrowser/hv_battle_ponychart.py
hvbrowser/hv_battle_skill_manager.py
hvbrowser/pause_controller.py
hvbrowser/py.typed
hvbrowser/hv_battle_ponychart_ml/thresholds.json
hvbrowser/hv_battle_ponychart_ml/weights.npz
hbrowser-0.11.7.dist-info/METADATA
hbrowser-0.11.7.dist-info/WHEEL
hbrowser-0.11.7.dist-info/top_level.txt
hbrowser-0.11.7.dist-info/RECORD
